rdf_expressionizer/__init__.py
rdf_expressionizer/cli.py
rdf_expressionizer/main.py
rdf_expressionizer/mappings/__init__.py
rdf_expressionizer/mappings/bfo_xbfo_mappings.csv
rdf_expressionizer/ontology/bfo_bridge.owl
rdf_expressionizer/ontology/cob-augmented-tidy.owl
rdf_expressionizer/ontology/ro-rewired-tidy.owl
rdf_expressionizer/ontology/xbfo.owl
rdf_expressionizer/ontology/xbfo_template.csv
rdf_expressionizer-0.1.0.dist-info/LICENSE
rdf_expressionizer-0.1.0.dist-info/METADATA
rdf_expressionizer-0.1.0.dist-info/WHEEL
rdf_expressionizer-0.1.0.dist-info/entry_points.txt
rdf_expressionizer-0.1.0.dist-info/RECORD
