Metadata-Version: 2.1
Name: rdf-expressionizer
Version: 0.1.0
Summary: rdf-expressionizer
License: BSD-3
Author: Author 1
Author-email: author@org.org
Requires-Python: >=3.9,<4.0
Classifier: License :: Other/Proprietary License
Classifier: Programming Language :: Python :: 3
Classifier: Programming Language :: Python :: 3.9
Classifier: Programming Language :: Python :: 3.10
Classifier: Programming Language :: Python :: 3.11
Classifier: Programming Language :: Python :: 3.12
Requires-Dist: click
Requires-Dist: curies (>=0.7.4,<0.8.0)
Requires-Dist: importlib-metadata (>=4.8.0,<5.0.0)
Requires-Dist: pyoxigraph (>=0.3.22,<0.4.0)
Requires-Dist: rdflib (>=7.0.0,<8.0.0)
